setup.py
multiblend/__init__.py
multiblend/dispatcher.py
multiblend/logging.py
multiblend/node.py
multiblend/popen.py
multiblend.egg-info/PKG-INFO
multiblend.egg-info/SOURCES.txt
multiblend.egg-info/dependency_links.txt
multiblend.egg-info/entry_points.txt
multiblend.egg-info/top_level.txt