Metadata-Version: 1.0
Name: multiblend
Version: 1.4
Summary: Distributed rendering with Blender
Home-page: http://www.stuvel.eu/multiblend
Author: Sybren A. Stuvel
Author-email: sybren@stuvel.eu
License: GPL
Platform: UNKNOWN
Classifier: Development Status :: 4 - Beta
Classifier: Intended Audience :: End Users/Desktop
Classifier: License :: OSI Approved :: GNU General Public License (GPL)
Classifier: Operating System :: OS Independent
Classifier: Programming Language :: Python
Classifier: Natural Language :: English
